jaas_ai/__init__.py
jaas_ai/main.py
jaas_ai/version.py
jaas_ai-0.1.10.dist-info/licenses/LICENSE
jaas_ai-0.1.10.dist-info/METADATA
jaas_ai-0.1.10.dist-info/WHEEL
jaas_ai-0.1.10.dist-info/top_level.txt
jaas_ai-0.1.10.dist-info/RECORD
